gorilla/__init__.py
gorilla/version.py
gorilla/config/__init__.py
gorilla/config/_config.py
gorilla/config/backup.py
gorilla/config/config.py
gorilla/config/logging.py
gorilla/core/__init__.py
gorilla/core/comm.py
gorilla/core/dist.py
gorilla/core/env.py
gorilla/core/fp16.py
gorilla/core/launch.py
gorilla/core/misc.py
gorilla/core/registry.py
gorilla/core/setup.py
gorilla/data/__init__.py
gorilla/data/dataloaders.py
gorilla/data/dataset_wrappers.py
gorilla/data/samplers.py
gorilla/evaluation/__init__.py
gorilla/evaluation/evaluator.py
gorilla/evaluation/testing.py
gorilla/evaluation/metric/__init__.py
gorilla/evaluation/metric/classification.py
gorilla/fileio/__init__.py
gorilla/fileio/file_client.py
gorilla/fileio/image_io.py
gorilla/fileio/io.py
gorilla/fileio/parse.py
gorilla/fileio/handlers/__init__.py
gorilla/fileio/handlers/base.py
gorilla/fileio/handlers/json_handler.py
gorilla/fileio/handlers/pickle_handler.py
gorilla/fileio/handlers/python_handler.py
gorilla/fileio/handlers/txt_handler.py
gorilla/fileio/handlers/yaml_handler.py
gorilla/losses/__init__.py
gorilla/losses/dice_loss.py
gorilla/losses/focal_loss.py
gorilla/losses/giou_loss.py
gorilla/losses/iou_guided_loss.py
gorilla/losses/label_smooth_ce_loss.py
gorilla/losses/lovasz_loss.py
gorilla/losses/regression_loss.py
gorilla/losses/smooth_l1_loss.py
gorilla/nn/__init__.py
gorilla/nn/alexnet.py
gorilla/nn/conv.py
gorilla/nn/fc.py
gorilla/nn/gcn.py
gorilla/nn/layer_builder.py
gorilla/nn/resnet.py
gorilla/nn/transformer.py
gorilla/nn/vgg.py
gorilla/nn/weight_init.py
gorilla/solver/__init__.py
gorilla/solver/base_solver.py
gorilla/solver/build.py
gorilla/solver/checkpoint.py
gorilla/solver/data.py
gorilla/solver/grad_clipper.py
gorilla/solver/log_buffer.py
gorilla/solver/lr_scheduler.py
gorilla/solver/optimizer.py
gorilla/solver/hook/__init__.py
gorilla/solver/hook/callback.py
gorilla/solver/hook/checkpoint.py
gorilla/solver/hook/hook.py
gorilla/solver/hook/iter_timer.py
gorilla/solver/hook/memory.py
gorilla_core-0.2.7.8.dist-info/LICENSE
gorilla_core-0.2.7.8.dist-info/METADATA
gorilla_core-0.2.7.8.dist-info/WHEEL
gorilla_core-0.2.7.8.dist-info/top_level.txt
gorilla_core-0.2.7.8.dist-info/RECORD
