Metadata-Version: 2.1
Name: gorilla-core
Version: 0.2.7.8
Summary: ToolBox Package for Gorilla-Lab using PyTorch
Home-page: UNKNOWN
Author: Gorilla Authors
Author-email: mszhihaoliang@mail.scut.edu.cn
License: MIT
Platform: UNKNOWN
Requires-Dist: numpy
Requires-Dist: tqdm
Requires-Dist: tensorboardX
Requires-Dist: gpustat
Requires-Dist: pyyaml
Requires-Dist: addict
Requires-Dist: yapf
Requires-Dist: termcolor
Requires-Dist: tabulate
Requires-Dist: pynvml
Requires-Dist: pytest
Requires-Dist: lmdb
